pyfamilyhublocal
