Metadata-Version: 1.1
Name: python-family-hub-local
Version: 0.0.2
Summary: Python API for accessing information from Samsung FamilyHub fridges locally.
Home-page: https://github.com/Klathmon/python-family-hub-local
Author: Gregory Benner
Author-email: gregbenner1@gmail.com
License: MIT
Download-URL: https://github.com/Klathmon/python-family-hub-local/archive/0.0.2.tar.gz
Platform: UNKNOWN
